Metadata-Version: 1.0
Name: try-package
Version: 0.1
Summary: Try upload a package to PiPy
Home-page: http://github.com/storborg/funniest
Author: riversky0014
Author-email: riversky0014@gmail.com
License: MIT
Platform: UNKNOWN
